{"nodes": [{"id": "users_j_desktop_\u6d41\u4e91\u667a\u70ac\u65b9\u6848_\u6d41\u4e91\u667a\u70ac\u4f01\u4e1a\u6587\u6863\u5e93_ai\u77e5\u8bc6\u5e93_10_\u5e38\u89c1\u95ee\u9898faq_md", "label": "10_\u5e38\u89c1\u95ee\u9898FAQ.md", "file_type": "document", "source_file": "/Users/j/Desktop/\u6d41\u4e91\u667a\u70ac\u65b9\u6848/\u6d41\u4e91\u667a\u70ac\u4f01\u4e1a\u6587\u6863\u5e93/AI\u77e5\u8bc6\u5e93/10_\u5e38\u89c1\u95ee\u9898FAQ.md", "source_location": "L1"}, {"id": "ai\u77e5\u8bc6\u5e93_10_\u5e38\u89c1\u95ee\u9898faq_\u6d41\u4e91\u667a\u70ac_\u5e38\u89c1\u95ee\u9898_faq", "label": "\u6d41\u4e91\u667a\u70ac \u00b7 \u5e38\u89c1\u95ee\u9898 FAQ", "file_type": "document", "source_file": "/Users/j/Desktop/\u6d41\u4e91\u667a\u70ac\u65b9\u6848/\u6d41\u4e91\u667a\u70ac\u4f01\u4e1a\u6587\u6863\u5e93/AI\u77e5\u8bc6\u5e93/10_\u5e38\u89c1\u95ee\u9898FAQ.md", "source_location": "L1"}, {"id": "ai\u77e5\u8bc6\u5e93_10_\u5e38\u89c1\u95ee\u9898faq_\u4ef7\u683c\u76f8\u5173", "label": "\u4ef7\u683c\u76f8\u5173", "file_type": "document", "source_file": "/Users/j/Desktop/\u6d41\u4e91\u667a\u70ac\u65b9\u6848/\u6d41\u4e91\u667a\u70ac\u4f01\u4e1a\u6587\u6863\u5e93/AI\u77e5\u8bc6\u5e93/10_\u5e38\u89c1\u95ee\u9898FAQ.md", "source_location": "L3"}, {"id": "ai\u77e5\u8bc6\u5e93_10_\u5e38\u89c1\u95ee\u9898faq_\u4ea4\u4ed8\u76f8\u5173", "label": "\u4ea4\u4ed8\u76f8\u5173", "file_type": "document", "source_file": "/Users/j/Desktop/\u6d41\u4e91\u667a\u70ac\u65b9\u6848/\u6d41\u4e91\u667a\u70ac\u4f01\u4e1a\u6587\u6863\u5e93/AI\u77e5\u8bc6\u5e93/10_\u5e38\u89c1\u95ee\u9898FAQ.md", "source_location": "L33"}, {"id": "ai\u77e5\u8bc6\u5e93_10_\u5e38\u89c1\u95ee\u9898faq_\u552e\u540e\u76f8\u5173", "label": "\u552e\u540e\u76f8\u5173", "file_type": "document", "source_file": "/Users/j/Desktop/\u6d41\u4e91\u667a\u70ac\u65b9\u6848/\u6d41\u4e91\u667a\u70ac\u4f01\u4e1a\u6587\u6863\u5e93/AI\u77e5\u8bc6\u5e93/10_\u5e38\u89c1\u95ee\u9898FAQ.md", "source_location": "L47"}, {"id": "ai\u77e5\u8bc6\u5e93_10_\u5e38\u89c1\u95ee\u9898faq_\u652f\u4ed8\u76f8\u5173", "label": "\u652f\u4ed8\u76f8\u5173", "file_type": "document", "source_file": "/Users/j/Desktop/\u6d41\u4e91\u667a\u70ac\u65b9\u6848/\u6d41\u4e91\u667a\u70ac\u4f01\u4e1a\u6587\u6863\u5e93/AI\u77e5\u8bc6\u5e93/10_\u5e38\u89c1\u95ee\u9898FAQ.md", "source_location": "L65"}, {"id": "ai\u77e5\u8bc6\u5e93_10_\u5e38\u89c1\u95ee\u9898faq_\u5176\u4ed6", "label": "\u5176\u4ed6", "file_type": "document", "source_file": "/Users/j/Desktop/\u6d41\u4e91\u667a\u70ac\u65b9\u6848/\u6d41\u4e91\u667a\u70ac\u4f01\u4e1a\u6587\u6863\u5e93/AI\u77e5\u8bc6\u5e93/10_\u5e38\u89c1\u95ee\u9898FAQ.md", "source_location": "L75"}], "edges": [{"source": "users_j_desktop_\u6d41\u4e91\u667a\u70ac\u65b9\u6848_\u6d41\u4e91\u667a\u70ac\u4f01\u4e1a\u6587\u6863\u5e93_ai\u77e5\u8bc6\u5e93_10_\u5e38\u89c1\u95ee\u9898faq_md", "target": "ai\u77e5\u8bc6\u5e93_10_\u5e38\u89c1\u95ee\u9898faq_\u6d41\u4e91\u667a\u70ac_\u5e38\u89c1\u95ee\u9898_faq", "relation": "contains", "confidence": "EXTRACTED", "source_file": "/Users/j/Desktop/\u6d41\u4e91\u667a\u70ac\u65b9\u6848/\u6d41\u4e91\u667a\u70ac\u4f01\u4e1a\u6587\u6863\u5e93/AI\u77e5\u8bc6\u5e93/10_\u5e38\u89c1\u95ee\u9898FAQ.md", "source_location": "L1", "weight": 1.0}, {"source": "ai\u77e5\u8bc6\u5e93_10_\u5e38\u89c1\u95ee\u9898faq_\u6d41\u4e91\u667a\u70ac_\u5e38\u89c1\u95ee\u9898_faq", "target": "ai\u77e5\u8bc6\u5e93_10_\u5e38\u89c1\u95ee\u9898faq_\u4ef7\u683c\u76f8\u5173", "relation": "contains", "confidence": "EXTRACTED", "source_file": "/Users/j/Desktop/\u6d41\u4e91\u667a\u70ac\u65b9\u6848/\u6d41\u4e91\u667a\u70ac\u4f01\u4e1a\u6587\u6863\u5e93/AI\u77e5\u8bc6\u5e93/10_\u5e38\u89c1\u95ee\u9898FAQ.md", "source_location": "L3", "weight": 1.0}, {"source": "ai\u77e5\u8bc6\u5e93_10_\u5e38\u89c1\u95ee\u9898faq_\u6d41\u4e91\u667a\u70ac_\u5e38\u89c1\u95ee\u9898_faq", "target": "ai\u77e5\u8bc6\u5e93_10_\u5e38\u89c1\u95ee\u9898faq_\u4ea4\u4ed8\u76f8\u5173", "relation": "contains", "confidence": "EXTRACTED", "source_file": "/Users/j/Desktop/\u6d41\u4e91\u667a\u70ac\u65b9\u6848/\u6d41\u4e91\u667a\u70ac\u4f01\u4e1a\u6587\u6863\u5e93/AI\u77e5\u8bc6\u5e93/10_\u5e38\u89c1\u95ee\u9898FAQ.md", "source_location": "L33", "weight": 1.0}, {"source": "ai\u77e5\u8bc6\u5e93_10_\u5e38\u89c1\u95ee\u9898faq_\u6d41\u4e91\u667a\u70ac_\u5e38\u89c1\u95ee\u9898_faq", "target": "ai\u77e5\u8bc6\u5e93_10_\u5e38\u89c1\u95ee\u9898faq_\u552e\u540e\u76f8\u5173", "relation": "contains", "confidence": "EXTRACTED", "source_file": "/Users/j/Desktop/\u6d41\u4e91\u667a\u70ac\u65b9\u6848/\u6d41\u4e91\u667a\u70ac\u4f01\u4e1a\u6587\u6863\u5e93/AI\u77e5\u8bc6\u5e93/10_\u5e38\u89c1\u95ee\u9898FAQ.md", "source_location": "L47", "weight": 1.0}, {"source": "ai\u77e5\u8bc6\u5e93_10_\u5e38\u89c1\u95ee\u9898faq_\u6d41\u4e91\u667a\u70ac_\u5e38\u89c1\u95ee\u9898_faq", "target": "ai\u77e5\u8bc6\u5e93_10_\u5e38\u89c1\u95ee\u9898faq_\u652f\u4ed8\u76f8\u5173", "relation": "contains", "confidence": "EXTRACTED", "source_file": "/Users/j/Desktop/\u6d41\u4e91\u667a\u70ac\u65b9\u6848/\u6d41\u4e91\u667a\u70ac\u4f01\u4e1a\u6587\u6863\u5e93/AI\u77e5\u8bc6\u5e93/10_\u5e38\u89c1\u95ee\u9898FAQ.md", "source_location": "L65", "weight": 1.0}, {"source": "ai\u77e5\u8bc6\u5e93_10_\u5e38\u89c1\u95ee\u9898faq_\u6d41\u4e91\u667a\u70ac_\u5e38\u89c1\u95ee\u9898_faq", "target": "ai\u77e5\u8bc6\u5e93_10_\u5e38\u89c1\u95ee\u9898faq_\u5176\u4ed6", "relation": "contains", "confidence": "EXTRACTED", "source_file": "/Users/j/Desktop/\u6d41\u4e91\u667a\u70ac\u65b9\u6848/\u6d41\u4e91\u667a\u70ac\u4f01\u4e1a\u6587\u6863\u5e93/AI\u77e5\u8bc6\u5e93/10_\u5e38\u89c1\u95ee\u9898FAQ.md", "source_location": "L75", "weight": 1.0}], "input_tokens": 0, "output_tokens": 0}